<?xml version="1.0" encoding="utf-8"?>
<!DOCTYPE hibernate-mapping PUBLIC "-//Hibernate/Hibernate Mapping DTD 3.0//EN"
"http://hibernate.sourceforge.net/hibernate-mapping-3.0.dtd">
<!-- Mapping file autogenerated by MyEclipse Persistence Tools -->
<hibernate-mapping>
	<class name="com.eyuan.domain.MovieShowInfo" table="movie_show_info"
		catalog="eyuandb">
		<cache usage="read-write" region="com.eyuan.domain.MovieShowInfo"/>
		<id name="showId" type="java.lang.Long">
			<column name="show_id" />
			<generator class="native"></generator>
		</id>
		<property name="showDate" type="java.lang.String">
			<column name="show_date" length="20" />
		</property>
		<property name="showTime" type="java.lang.String">
			<column name="show_time" length="10" />
		</property>
		<property name="showPrice" type="java.lang.Double">
			<column name="show_price" />
		</property>
		<property name="ticketLeft" type="java.lang.Integer">
			<column name="ticket_left" />
		</property>
		<many-to-one name="movieInfo" class="com.eyuan.domain.MovieInfo"
			lazy="false" cascade="save-update">
			<column name="movie_id" />
		</many-to-one>
		<set name="showSeatRelations" inverse="true" lazy="false">
			<key>
				<column name="show_id" />
			</key>
			<one-to-many class="com.eyuan.domain.ShowSeatRelation" />
		</set>
		<set name="userTicketInfos" inverse="true">
			<key>
				<column name="show_id" />
			</key>
			<one-to-many class="com.eyuan.domain.UserTicketInfo" />
		</set>
		<set name="simpleTicketInfos" lazy="false">
			<key>
				<column name="show_id" />
			</key>
			<one-to-many class="com.eyuan.domain.SimpleTicketInfo" />
		</set>
	</class>
</hibernate-mapping>
